{
  "presets": [
    [
      "@babel/preset-env",
      {
        "targets": {
          "edge": "17",
          "firefox": "60",
          "chrome": "67",
          "safari": "11.1"
        },
        "useBuiltIns": "usage",
        "corejs": "3.6.5"
      }
    ]
  ],
  "plugins": [
    //   ["@babel/plugin-proposal-decorators", { "legacy": true }],
    //   "@babel/plugin-transform-runtime",
    //   "babel-plugin-add-module-exports",
    //   "@babel/plugin-proposal-class-properties",
    //   "@babel/plugin-syntax-dynamic-import",
    //   "babel-plugin-react-docgen"
    "transform-class-properties",
    "inline-svg"
  ]
}
